{
  "question_id": "eprawnik_00752",
  "source_url": "https://e-prawnik.pl/forum/ubezpieczenie-telefonu.html",
  "fetch_url": "https://e-prawnik.pl/forum/ubezpieczenie-telefonu.html",
  "archive_file": "e_prawnik/eprawnik_00752.html",
  "http_status": 200,
  "content_type": "text/html; charset=utf-8",
  "size_bytes": 57074,
  "sha256": "4f86a209ecd1b652b08fbefc30d2f729e995e6a4686f54dd28e52771d83e8b78",
  "download_date": "2026-05-16T07:37:33Z",
  "duration_sec": 0.121,
  "attempt": 1,
  "error": false,
  "error_reason": null
}