{
  "id": "f9ec8199292d6dd9",
  "url": "https://www.pip.gov.pl/files/126/Dla-pracownikow/548/prace-kombajnem-zobozowym.pdf",
  "source": "pip",
  "topic_ids": [
    "kp_urlop"
  ],
  "layer": "L2",
  "format": "pdf",
  "fetched_at": "2026-04-25T09:59:14Z",
  "http_status": 200,
  "content_type": "application/pdf",
  "bytes": 420816,
  "relative_path": "raw/pip/prace-kombajnem-zobozowym.pdf",
  "title": "BHP \n    \n    \n     \n\n\n        \n        \n         Prace kombajnem zbożowym",
  "last_modified": "",
  "is_official": true,
  "eli_id": "",
  "parent_url": "https://www.pip.gov.pl/publikacje/publikacje-dla-pracownikow?start=54",
  "discovery_source": "paginacja",
  "sha256": "f9ec8199292d6dd93a1e0e5804ffedeb386c9e230aedc677db99b19012a24636",
  "quality_flag": "accepted",
  "notes": "",
  "headers": {
    "content-disposition": "attachment; filename=\"prace kombajnem zobozowym.pdf\"",
    "content-description": "File Transfer",
    "content-transfer-encoding": "binary",
    "expires": "0",
    "cache-control": "must-revalidate, post-check=0, pre-check=0,private, must-revalidate",
    "pragma": "public",
    "x-content-type-options": "nosniff",
    "vary": "Accept-Encoding,User-Agent",
    "content-encoding": "gzip",
    "content-type": "application/octet-stream",
    "date": "Sat, 25 Apr 2026 09:59:13 GMT",
    "server": "Apache/2",
    "transfer-encoding": "chunked"
  }
}