{
  "question_id": "eporady24_00264",
  "source_url": "https://www.eporady24.pl/problemy-po-naprawie-samochodu-w-serwisie,pytania,4,47,27241.html",
  "fetch_url": "https://www.eporady24.pl/problemy-po-naprawie-samochodu-w-serwisie,pytania,4,47,27241.html",
  "archive_file": "legal_other/eporady24_00264.html",
  "http_status": 200,
  "content_type": "text/html",
  "size_bytes": 21193,
  "sha256": "6453eb1ad33a7303331f0c662ced6c6b413dfde22aa5066ee4bd228a508495e8",
  "download_date": "2026-05-16T08:26:18Z",
  "duration_sec": 0.24,
  "attempt": 1,
  "error": false,
  "error_reason": null
}